cqr/__init__.py
cqr/cvxpy_interface.py
cqr/equilibrate.py
cqr/solver.py
cqr/test.py
cqr-0.1.0.dist-info/COPYING
cqr-0.1.0.dist-info/METADATA
cqr-0.1.0.dist-info/WHEEL
cqr-0.1.0.dist-info/top_level.txt
cqr-0.1.0.dist-info/RECORD
